tech4354353/__init__.py
tech4354353/tech4354353.py
tech4354353-1.3.dist-info/METADATA
tech4354353-1.3.dist-info/WHEEL
tech4354353-1.3.dist-info/top_level.txt
tech4354353-1.3.dist-info/RECORD
